knactor/__init__.py
knactor-0.1.0.dist-info/WHEEL
knactor-0.1.0.dist-info/METADATA
knactor-0.1.0.dist-info/RECORD
